nsw_topo_split/__init__.py
nsw_topo_split/__main__.py
nsw_topo_split/_main.py
nsw_topo_split/py.typed
nsw_topo_split-0.1.0b3.dist-info/LICENSE
nsw_topo_split-0.1.0b3.dist-info/METADATA
nsw_topo_split-0.1.0b3.dist-info/WHEEL
nsw_topo_split-0.1.0b3.dist-info/entry_points.txt
nsw_topo_split-0.1.0b3.dist-info/top_level.txt
nsw_topo_split-0.1.0b3.dist-info/RECORD
