Metadata-Version: 2.2
Name: nsw-topo-split
Version: 0.1.0b3
Summary: A tool for downloading and nicely splitting NSW Spatial Services topographic maps across smaller pages
Author: Thomas Schanzer
Project-URL: Documentation, https://github.com/tschanzer/nsw-topo-split/blob/v0.1.0b3/README.md
Project-URL: Repository, https://github.com/tschanzer/nsw-topo-split
Project-URL: Issues, https://github.com/tschanzer/nsw-topo-split/issues
Classifier: Development Status :: 4 - Beta
Classifier: Operating System :: OS Independent
Classifier: License :: OSI Approved :: MIT License
Classifier: Programming Language :: Python :: 3
Classifier: Programming Language :: Python :: 3.9
Classifier: Programming Language :: Python :: 3.10
Classifier: Programming Language :: Python :: 3.11
Classifier: Programming Language :: Python :: 3.12
Classifier: Programming Language :: Python :: 3.13
Classifier: Typing :: Typed
Requires-Python: >=3.9
License-File: LICENSE
Requires-Dist: pymupdf
Provides-Extra: dev
Requires-Dist: black; extra == "dev"
Requires-Dist: pylint; extra == "dev"
Requires-Dist: mypy; extra == "dev"
Requires-Dist: isort; extra == "dev"
Requires-Dist: pip-tools; extra == "dev"
Requires-Dist: pre-commit; extra == "dev"
